kyupy/__init__.py
kyupy/bench.py
kyupy/circuit.py
kyupy/def_file.py
kyupy/logic.py
kyupy/logic_sim.py
kyupy/sdf.py
kyupy/sim.py
kyupy/stil.py
kyupy/techlib.py
kyupy/verilog.py
kyupy/wave_sim.py
kyupy-0.0.5.dist-info/METADATA
kyupy-0.0.5.dist-info/WHEEL
kyupy-0.0.5.dist-info/licenses/LICENSE.txt
kyupy-0.0.5.dist-info/RECORD
