Metadata-Version: 2.4
Name: kyupy
Version: 0.0.5
Summary: High-performance processing and analysis of non-hierarchical VLSI designs
Project-URL: homepage, https://github.com/s-holst/kyupy
Author-email: Stefan Holst <mail@s-holst.de>
License-Expression: MIT
License-File: LICENSE.txt
Classifier: Development Status :: 3 - Alpha
Classifier: Environment :: GPU :: NVIDIA CUDA
Classifier: Intended Audience :: Science/Research
Classifier: License :: OSI Approved :: MIT License
Classifier: Operating System :: OS Independent
Classifier: Programming Language :: Python :: 3
Classifier: Topic :: Scientific/Engineering :: Electronic Design Automation (EDA)
Requires-Dist: lark-parser>=0.8.0
Requires-Dist: numpy>=1.17.0
